donald_hello_pp/__init__.py
donald_hello_pp/main.py
donald_hello_pp-0.2.3.dist-info/METADATA
donald_hello_pp-0.2.3.dist-info/WHEEL
donald_hello_pp-0.2.3.dist-info/top_level.txt
donald_hello_pp-0.2.3.dist-info/RECORD
